{
  "type": "join",
  "neverRecomputeExistingPartitions": false,
  "optionalDependencies": false,
  "customMeta": {
    "kv": {}
  },
  "redispatchPartitioning": false,
  "maxRunningActivities": 0,
  "variables": {},
  "dkuProperties": [],
  "inputs": {
    "main": {
      "items": [
        {
          "ref": "insurance_customer_demog",
          "deps": []
        },
        {
          "ref": "insurance_customer_details",
          "deps": []
        },
        {
          "ref": "insurance_customer_economic",
          "deps": []
        }
      ]
    }
  },
  "outputs": {
    "main": {
      "items": [
        {
          "ref": "insurance_customer_demog_joined",
          "appendMode": false
        }
      ]
    }
  },
  "labels": [],
  "versionTag": {
    "versionNumber": 2,
    "lastModifiedBy": {
      "login": "admin"
    },
    "lastModifiedOn": 1635702335894
  },
  "creationTag": {
    "versionNumber": 0,
    "lastModifiedBy": {
      "login": "admin"
    },
    "lastModifiedOn": 1635701987673
  },
  "tags": [],
  "customFields": {},
  "checklists": {
    "checklists": []
  }
}